ChangeLog
LICENSE
MANIFEST.in
README
TODO
setup.py
Isomyr.egg-info/PKG-INFO
Isomyr.egg-info/SOURCES.txt
Isomyr.egg-info/dependency_links.txt
Isomyr.egg-info/top_level.txt
admin/__init__.py
admin/generateAPIDoc.py
admin/generateUploadSetup.py
admin/getLatestPayloads.py
admin/testDocs.py
admin/testRunner.py
docs/DEPENDENCIES.txt
docs/HISTORY.txt
docs/INSTALL.txt
docs/PRELUDE.txt
docs/USAGE.txt
examples/OpenGround/background.png
examples/OpenGround/openground.py
examples/OpenGround/sliceBackground.py
examples/OpenGround/titlebar.png
examples/OpenGround/backgrounds/1084x126.png
examples/OpenGround/backgrounds/1084x302.png
examples/OpenGround/backgrounds/1258x214.png
examples/OpenGround/backgrounds/1258x390.png
examples/OpenGround/backgrounds/214x214.png
examples/OpenGround/backgrounds/214x390.png
examples/OpenGround/backgrounds/388x126.png
examples/OpenGround/backgrounds/388x302.png
examples/OpenGround/backgrounds/562x214.png
examples/OpenGround/backgrounds/562x390.png
examples/OpenGround/backgrounds/736x126.png
examples/OpenGround/backgrounds/736x302.png
examples/OpenGround/backgrounds/910x214.png
examples/OpenGround/backgrounds/910x390.png
examples/OpenGround/explorer/east/large/12_02_01.gif
examples/OpenGround/explorer/east/large/12_02_02.gif
examples/OpenGround/explorer/east/large/12_02_03.gif
examples/OpenGround/explorer/east/large/12_02_04.gif
examples/OpenGround/explorer/east/large/12_02_05.gif
examples/OpenGround/explorer/east/large/12_02_06.gif
examples/OpenGround/explorer/east/large/12_02_07.gif
examples/OpenGround/explorer/east/large/12_02_08.gif
examples/OpenGround/explorer/east/large/12_02_09.gif
examples/OpenGround/explorer/east/large/12_02_10.gif
examples/OpenGround/explorer/east/large/12_02_11.gif
examples/OpenGround/explorer/east/large/12_02_12.gif
examples/OpenGround/explorer/east/large/12_02_13.gif
examples/OpenGround/explorer/east/large/12_02_14.gif
examples/OpenGround/explorer/east/large/12_02_15.gif
examples/OpenGround/explorer/east/small/12_02_01.gif
examples/OpenGround/explorer/east/small/12_02_02.gif
examples/OpenGround/explorer/east/small/12_02_03.gif
