Metadata-Version: 1.0
Name: Isomyr
Version: 0.1
Summary: A Python Isometric Game Engine.
Home-page: http://launchpad.net/isomyr
Author: Duncan McGreggor
Author-email: oubiwann@adytum.us
License: BSD, GPL
Platform: UNKNOWN
Classifier: Development Status :: 4 - Beta
Classifier: Intended Audience :: Developers
Classifier: Programming Language :: Python
